LICENSE.txt
setup.cfg
setup.py
hcarpy/Toolbox.py
hcarpy/__init__.py
hcarpy.egg-info/PKG-INFO
hcarpy.egg-info/SOURCES.txt
hcarpy.egg-info/dependency_links.txt
hcarpy.egg-info/top_level.txt