Metadata-Version: 2.1
Name: hcarpy
Version: 0.0.6
Summary: TYPE YOUR DESCRIPTION HERE
Home-page: 
Download-URL: https://github.deshaw.com/hcar/hcarpy/archive/refs/tags/v0.0.6.tar.gz
Author: JANELLE TANG
Author-email: tangj@deshaw.com
License: MIT
Keywords: HCAR,CLEANING,WRANGLING
Classifier: Development Status :: 3 - Alpha
Classifier: Intended Audience :: Developers
Classifier: Topic :: Software Development :: Build Tools
Classifier: License :: OSI Approved :: MIT License
Classifier: Programming Language :: Python :: 3
Classifier: Programming Language :: Python :: 3.6
Classifier: Programming Language :: Python :: 3.7
Classifier: Programming Language :: Python :: 3.8
Classifier: Programming Language :: Python :: 3.9
Classifier: Programming Language :: Python :: 3.10
License-File: LICENSE.txt
